tap_redcap/__init__.py
tap_redcap/client.py
tap_redcap/streams.py
tap_redcap/tap.py
tap_redcap/tests/__init__.py
tap_redcap/tests/test_core.py
tap_redcap-0.0.4.dist-info/entry_points.txt
tap_redcap-0.0.4.dist-info/WHEEL
tap_redcap-0.0.4.dist-info/METADATA
tap_redcap-0.0.4.dist-info/RECORD
